{
"metabolites":[
{
"id":"Glc",
"name":"",
"compartment":"Biomass"
},
{
"id":"AA",
"name":"",
"compartment":"Biomass"
},
{
"id":"Bio",
"name":"",
"compartment":"Biomass"
}
],
"reactions":[
{
"id":"v0",
"name":"v0",
"metabolites":{
"Glc":1
},
"lower_bound":1,
"upper_bound":1,
"gene_reaction_rule":""
},
{
"id":"v1",
"name":"v1",
"metabolites":{
"AA":1,
"Glc":-1
},
"lower_bound":0,
"upper_bound":1000,
"gene_reaction_rule":""
},
{
"id":"v2",
"name":"v2",
"metabolites":{
"AA":-9.09,
"Bio":1
},
"lower_bound":0,
"upper_bound":1000,
"gene_reaction_rule":""
},
{
"id":"v3",
"name":"v3",
"metabolites":{
"Bio":-1
},
"lower_bound":0,
"upper_bound":1000,
"gene_reaction_rule":"",
"objective_coefficient":1.0
}
],
"genes":[],
"id":"Model",
"compartments":{
"Biomass":""
},
"version":"1"
}